wavelet_matrix/__init__.py
wavelet_matrix/__init__.pyi
wavelet_matrix/py.typed
wavelet_matrix/wavelet_matrix.cpython-314t-aarch64-linux-gnu.so
wavelet_matrix-2.0.9.dist-info/METADATA
wavelet_matrix-2.0.9.dist-info/WHEEL
wavelet_matrix-2.0.9.dist-info/licenses/LICENSE
wavelet_matrix-2.0.9.dist-info/RECORD
