Metadata-Version: 2.4
Name: wavelet-matrix
Version: 2.0.9
Classifier: Intended Audience :: Developers
Classifier: Intended Audience :: Science/Research
Classifier: Intended Audience :: Information Technology
Classifier: License :: OSI Approved :: MIT License
Classifier: Programming Language :: Python :: 3
Classifier: Programming Language :: Python :: 3.9
Classifier: Programming Language :: Python :: 3.10
Classifier: Programming Language :: Python :: 3.11
Classifier: Programming Language :: Python :: 3.12
Classifier: Programming Language :: Python :: 3.13
Classifier: Programming Language :: Python :: 3.14
Classifier: Programming Language :: Python :: Implementation :: CPython
Classifier: Programming Language :: Python :: Implementation :: PyPy
Classifier: Topic :: Software Development :: Libraries :: Python Modules
Classifier: Topic :: Scientific/Engineering :: Information Analysis
Classifier: Topic :: Scientific/Engineering :: Mathematics
Classifier: Typing :: Typed
Requires-Dist: pdoc>=16.0 ; extra == 'dev'
Requires-Dist: ruff>=0.14 ; extra == 'dev'
Requires-Dist: pytest>=7.0 ; extra == 'test'
Requires-Dist: pytest-benchmark>=4.0 ; extra == 'test'
Provides-Extra: dev
Provides-Extra: test
License-File: LICENSE
Summary: High-performance indexed sequence data structure powered by Rust, supporting fast rank/select and range queries.
Keywords: wavelet matrix,data structure,algorithm,sequence index,rank,select,quantile,top-k,range query,dynamic update,indexing,succinct
Author: Koki Watanabe
Requires-Python: >=3.9
Project-URL: documentation, https://math-hiyoko.github.io/wavelet-matrix
Project-URL: homepage, https://github.com/math-hiyoko/wavelet-matrix
Project-URL: repository, https://github.com/math-hiyoko/wavelet-matrix
